greedyFAS/__init__.py
greedyFAS/calcFAD.py
greedyFAS/calcFAS.py
greedyFAS/calcFASmulti.py
greedyFAS/complexityFAS.py
greedyFAS/domainFAS.py
greedyFAS/extractAnnoFAS.py
greedyFAS/fdogFAS.py
greedyFAS/getOverlapStats.py
greedyFAS/mergeAnno.py
greedyFAS/mergeJson.py
greedyFAS/setupFAS.py
greedyFAS/splitDomains.py
greedyFAS/tsv2json.py
greedyFAS/updateAnno.py
greedyFAS/updateJson.py
greedyFAS/annoFAS/__init__.py
greedyFAS/annoFAS/annoFAS.py
greedyFAS/annoFAS/annoModules.py
greedyFAS/annoFAS/annoParserFAS.py
greedyFAS/annoFAS/checkAnno.py
greedyFAS/annoFAS/getAnnoVersion.py
greedyFAS/annoFAS/getProtByAnno.py
greedyFAS/annoFAS/test_annofas.fa
greedyFAS/annoFAS/updateAnnoFile.py
greedyFAS/disorderFAS/__init__.py
greedyFAS/disorderFAS/install_aucpred.py
greedyFAS/disorderFAS/predict_disorder.py
greedyFAS/mainFAS/__init__.py
greedyFAS/mainFAS/fadMain.py
greedyFAS/mainFAS/fadScoring.py
greedyFAS/mainFAS/fasInput.py
greedyFAS/mainFAS/fasOutput.py
greedyFAS/mainFAS/fasPathing.py
greedyFAS/mainFAS/fasScoring.py
greedyFAS/mainFAS/fasWeighting.py
greedyFAS/mainFAS/greedyFAS.py
greedyfas-1.18.21.dist-info/licenses/LICENSE
greedyfas-1.18.21.dist-info/METADATA
greedyfas-1.18.21.dist-info/WHEEL
greedyfas-1.18.21.dist-info/entry_points.txt
greedyfas-1.18.21.dist-info/top_level.txt
greedyfas-1.18.21.dist-info/RECORD
