Metadata-Version: 2.4
Name: greedyFAS
Version: 1.18.21
Summary: A tool to compare protein feature architectures
Home-page: https://github.com/BIONF/FAS
Author: Julian Dosch
Author-email: Dosch@bio.uni-frankfurt.de
License: GPL-3.0
Classifier: Environment :: Console
Classifier: Development Status :: 3 - Alpha
Classifier: Intended Audience :: End Users/Desktop
Classifier: License :: OSI Approved :: GNU General Public License v3 or later (GPLv3+)
Classifier: Natural Language :: English
Classifier: Programming Language :: Python :: 3
Requires-Python: >=3.12.0
License-File: LICENSE
Requires-Dist: biopython
Requires-Dist: tqdm
Requires-Dist: graphviz
Requires-Dist: gnureadline
Requires-Dist: GitPython
Requires-Dist: pathlib
Requires-Dist: requests
Dynamic: author
Dynamic: author-email
Dynamic: classifier
Dynamic: description
Dynamic: description-content-type
Dynamic: home-page
Dynamic: license
Dynamic: license-file
Dynamic: requires-dist
Dynamic: requires-python
Dynamic: summary
